auto_clash-0.1.1.dist-info/METADATA
auto_clash-0.1.1.dist-info/WHEEL
auto_clash-0.1.1.dist-info/entry_points.txt
auto_clash/__init__.py
auto_clash/clash.py
auto_clash/main.py
auto_clash-0.1.1.dist-info/RECORD
