Metadata-Version: 2.1
Name: auto-clash
Version: 0.1.1
Summary: Switch proxy nodes using the clash api
Author-Email: funcdefmain <741132517@qq.com>
License: MIT
Requires-Python: >=3.10
Requires-Dist: requests>=2.32.3
Requires-Dist: pyyaml>=6.0.2
Requires-Dist: loguru>=0.7.2
Requires-Dist: jsonpath>=0.82.2
